scrapy_deltafetch/__init__.py
scrapy_deltafetch/middleware.py
scrapy_deltafetch-2.1.0.dist-info/METADATA
scrapy_deltafetch-2.1.0.dist-info/WHEEL
scrapy_deltafetch-2.1.0.dist-info/top_level.txt
scrapy_deltafetch-2.1.0.dist-info/RECORD
