Metadata-Version: 2.2
Name: scrapy-deltafetch
Version: 2.1.0
Summary: Scrapy middleware to ignore previously crawled pages
Author-email: Zyte <opensource@zyte.com>
License: BSD
Project-URL: Homepage, http://github.com/scrapy-plugins/scrapy-deltafetch
Classifier: Development Status :: 4 - Beta
Classifier: License :: OSI Approved :: BSD License
Classifier: Operating System :: OS Independent
Classifier: Programming Language :: Python
Classifier: Programming Language :: Python :: 3
Classifier: Programming Language :: Python :: 3.9
Classifier: Programming Language :: Python :: 3.10
Classifier: Programming Language :: Python :: 3.11
Classifier: Programming Language :: Python :: 3.12
Classifier: Programming Language :: Python :: 3.13
Requires-Python: >=3.9
Requires-Dist: Scrapy>=1.1.0
